lizaiupload/__init__.py
lizaiupload/config.py
lizaiupload/constants.py
lizaiupload/datatypes.py
lizaiupload/helpers.py
lizaiupload/main.py
lizaiupload/upload.py
lizaiupload/uploader_service.py
lizaiupload-1.4.2.dist-info/entry_points.txt
lizaiupload-1.4.2.dist-info/LICENSE
lizaiupload-1.4.2.dist-info/METADATA
lizaiupload-1.4.2.dist-info/WHEEL
lizaiupload-1.4.2.dist-info/RECORD
