Metadata-Version: 2.3
Name: lizaiupload
Version: 1.4.2
Summary: A tool to upload folders with multipart upload.
Author: Victor Duong
Author-email: victor.duong@lizai.co
Requires-Python: >=3.6
Classifier: Programming Language :: Python :: 3
Classifier: License :: OSI Approved :: MIT License
Classifier: Operating System :: OS Independent
Requires-Dist: aiofiles (>=0.7.0,<0.8.0)
Requires-Dist: aiohttp (>=3.7.4,<4.0.0)
Requires-Dist: argparse (>=1.4.0,<2.0.0)
Requires-Dist: python-dotenv (>=0.19.0,<0.20.0)
Requires-Dist: requests (>=2.26.0,<3.0.0)
Requires-Dist: tenacity (>=8.0.1,<9.0.0)
Project-URL: Homepage, https://lizai.co
